comserde/__init__.py
comserde/composite.py
comserde/decoding.py
comserde/decorator.py
comserde/entry.py
comserde/error.py
comserde/primitive.py
comserde/types.py
comserde/vlq.py
comserde-0.2.0.dist-info/METADATA
comserde-0.2.0.dist-info/WHEEL
comserde-0.2.0.dist-info/top_level.txt
comserde-0.2.0.dist-info/RECORD
