Metadata-Version: 2.1
Name: comserde
Version: 0.2.0
Summary: Library for serializing data structures into compact binary data
License: EUPL-1.2
Project-URL: repository, https://github.com/slietar/comserde
Requires-Python: >=3.11
